README.md
setup.py
lianjia/__init__.py
lianjia/pyLianjia.py
lianjia.egg-info/PKG-INFO
lianjia.egg-info/SOURCES.txt
lianjia.egg-info/dependency_links.txt
lianjia.egg-info/requires.txt
lianjia.egg-info/top_level.txt