Metadata-Version: 1.0
Name: lianjia
Version: 0.2.0
Summary: time and path tool
Home-page: https://github.com/raymonYuan/raymonYuan.github.io
Author: raymonYuan
Author-email: 1131510575@qq.com
License: MIT Licence
Keywords: pip,pathtool,timetool,magetool,mage
Platform: any
